CSET/__init__.py
CSET/__main__.py
CSET/_common.py
CSET/graph.py
CSET/_workflow_utils/__init__.py
CSET/_workflow_utils/fetch_data.py
CSET/_workflow_utils/finish_website.py
CSET/_workflow_utils/preprocess.py
CSET/_workflow_utils/run_cset_recipe.py
CSET/_workflow_utils/send_email.py
CSET/operators/__init__.py
CSET/operators/_colorbar_definition.json
CSET/operators/_plot_page_template.html
CSET/operators/_stash_to_lfric.py
CSET/operators/_utils.py
CSET/operators/ageofair.py
CSET/operators/aggregate.py
CSET/operators/collapse.py
CSET/operators/constraints.py
CSET/operators/convection.py
CSET/operators/ensembles.py
CSET/operators/filters.py
CSET/operators/mesoscale.py
CSET/operators/misc.py
CSET/operators/plot.py
CSET/operators/read.py
CSET/operators/regrid.py
CSET/operators/transect.py
CSET/operators/write.py
CSET/recipes/CAPE_ratio_plot.yaml
CSET/recipes/Example_Gaussian_Spatial_Perturbation.yaml
CSET/recipes/Example_Uniform_Spatial_Perturbation.yaml
CSET/recipes/__init__.py
CSET/recipes/ageofair.yaml
CSET/recipes/example_DKE.yaml
CSET/recipes/example_combined_mask_addition.yaml
CSET/recipes/example_combined_mask_multiplication.yaml
CSET/recipes/example_simple_mask.yaml
CSET/recipes/example_spatial_plot_of_mask.yaml
CSET/recipes/generic_basic_qq_plot.yaml
CSET/recipes/generic_level_domain_mean_time_series.yaml
CSET/recipes/generic_level_domain_mean_time_series_case_aggregation_hour_of_day.yaml
CSET/recipes/generic_level_domain_mean_time_series_case_aggregation_lead_time.yaml
CSET/recipes/generic_level_domain_mean_time_series_case_aggregation_validity_time.yaml
CSET/recipes/generic_level_domain_mean_vertical_profile_series.yaml
CSET/recipes/generic_level_domain_mean_vertical_profile_series_case_aggregation_hour_of_day.yaml
CSET/recipes/generic_level_domain_mean_vertical_profile_series_case_aggregation_lead_time.yaml
CSET/recipes/generic_level_domain_mean_vertical_profile_series_case_aggregation_validity_time.yaml
CSET/recipes/generic_level_histogram_series.yaml
cset-25.5.2.dist-info/licenses/LICENCE
cset-25.5.2.dist-info/METADATA
cset-25.5.2.dist-info/WHEEL
cset-25.5.2.dist-info/entry_points.txt
cset-25.5.2.dist-info/top_level.txt
cset-25.5.2.dist-info/RECORD
