Metadata-Version: 2.4
Name: CSET
Version: 25.5.2
Summary: Toolkit for evaluation and investigation of numerical models for weather and climate applications.
Author: Met Office, NIWA
License-Expression: Apache-2.0
Project-URL: Documentation, https://metoffice.github.io/CSET
Project-URL: Source, https://github.com/MetOffice/CSET
Classifier: Development Status :: 4 - Beta
Classifier: Intended Audience :: Science/Research
Classifier: Operating System :: POSIX :: Linux
Classifier: Programming Language :: Python :: 3 :: Only
Classifier: Programming Language :: Python :: 3.11
Classifier: Programming Language :: Python :: 3.12
Classifier: Programming Language :: Python :: 3.13
Classifier: Programming Language :: Python
Classifier: Topic :: Scientific/Engineering :: Atmospheric Science
Classifier: Topic :: Scientific/Engineering :: GIS
Classifier: Topic :: Scientific/Engineering :: Visualization
Classifier: Topic :: Scientific/Engineering
Requires-Python: >=3.11
License-File: LICENCE
Requires-Dist: numpy
Requires-Dist: scitools-iris>=3.12.2
Requires-Dist: ruamel.yaml>=0.17
Requires-Dist: pygraphviz>=1.11
Requires-Dist: mo_pack>=0.3.0
Requires-Dist: isodate
Requires-Dist: markdown-it-py>=3.0
Requires-Dist: nc-time-axis
Requires-Dist: iris-grib
Dynamic: license-file
